rpc_call/__init__.py
rpc_call/async_client.py
rpc_call/helpers.py
rpc_call/server.py
rpc_call/sync_client.py
rpc_call/types.py
rpc_call-0.1.5.dist-info/METADATA
rpc_call-0.1.5.dist-info/WHEEL
rpc_call-0.1.5.dist-info/entry_points.txt
rpc_call-0.1.5.dist-info/RECORD
