Metadata-Version: 2.1
Name: rpc-call
Version: 0.1.5
Summary: 
Author: Artyom Syssolov
Author-email: artyom.syssolov@gmail.com
Requires-Python: >=3.7,<4.0
Classifier: Programming Language :: Python :: 3
Classifier: Programming Language :: Python :: 3.7
Classifier: Programming Language :: Python :: 3.8
Classifier: Programming Language :: Python :: 3.9
Classifier: Programming Language :: Python :: 3.10
Classifier: Programming Language :: Python :: 3.11
Requires-Dist: aio-pika (>=8.3.0,<9.0.0)
Requires-Dist: loguru (>=0.6.0,<0.7.0)
Requires-Dist: orjson (>=3.8.5,<4.0.0)
Requires-Dist: pika (>=1.3.1,<2.0.0)
Requires-Dist: pydantic (>=1.10.4,<2.0.0)
Requires-Dist: simplejson (>=3.18.1,<4.0.0)
